yadirstat/__init__.py
yadirstat/yadirstat.py
yadirstat-1.0.1.dist-info/LICENSE
yadirstat-1.0.1.dist-info/METADATA
yadirstat-1.0.1.dist-info/WHEEL
yadirstat-1.0.1.dist-info/top_level.txt
yadirstat-1.0.1.dist-info/RECORD
