Metadata-Version: 2.1
Name: yadirstat
Version: 1.0.1
Summary: Получение статистики из Яндекс Директ
Home-page: https://github.com/Lubiviy/yadirstat
Author: Lubiviy Alexander
Author-email: lybiviyalexandr@gmail.com
License: UNKNOWN
Platform: UNKNOWN
